pymatsci/__init__.py
pymatsci/abstract.py
pymatsci/correction.py
pymatsci/model.py
pymatsci/printout.py
pymatsci/processing.py
pymatsci/surface.py
pymatsci-1.0.1.dist-info/LICENSE
pymatsci-1.0.1.dist-info/METADATA
pymatsci-1.0.1.dist-info/WHEEL
pymatsci-1.0.1.dist-info/top_level.txt
pymatsci-1.0.1.dist-info/RECORD
