Metadata-Version: 2.1
Name: pymatsci
Version: 1.0.1
Summary: Python Materials Science
Home-page: https://pymatsci.readthedocs.io/en/latest/
Author: C.L. Qin
Author-email: clqin@foxmail.com
License: MIT License (MIT)
Requires-Python: >=3
License-File: LICENSE
Requires-Dist: numpy
Requires-Dist: pymatgen
